cloops/__init__.py
cloops/README.rst
cloops-1.0.2.dist-info/WHEEL
cloops-1.0.2.dist-info/METADATA
cloops-1.0.2.dist-info/RECORD
